chatterbox/__init__.py
chatterbox/mtl_tts.py
chatterbox/tts.py
chatterbox/vc.py
chatterbox/models/__init__.py
chatterbox/models/utils.py
chatterbox/models/s3gen/__init__.py
chatterbox/models/s3gen/configs.py
chatterbox/models/s3gen/const.py
chatterbox/models/s3gen/decoder.py
chatterbox/models/s3gen/f0_predictor.py
chatterbox/models/s3gen/flow.py
chatterbox/models/s3gen/flow_matching.py
chatterbox/models/s3gen/hifigan.py
chatterbox/models/s3gen/s3gen.py
chatterbox/models/s3gen/xvector.py
chatterbox/models/s3gen/matcha/decoder.py
chatterbox/models/s3gen/matcha/flow_matching.py
chatterbox/models/s3gen/matcha/text_encoder.py
chatterbox/models/s3gen/matcha/transformer.py
chatterbox/models/s3gen/transformer/__init__.py
chatterbox/models/s3gen/transformer/activation.py
chatterbox/models/s3gen/transformer/attention.py
chatterbox/models/s3gen/transformer/convolution.py
chatterbox/models/s3gen/transformer/embedding.py
chatterbox/models/s3gen/transformer/encoder_layer.py
chatterbox/models/s3gen/transformer/positionwise_feed_forward.py
chatterbox/models/s3gen/transformer/subsampling.py
chatterbox/models/s3gen/transformer/upsample_encoder.py
chatterbox/models/s3gen/utils/class_utils.py
chatterbox/models/s3gen/utils/mask.py
chatterbox/models/s3gen/utils/mel.py
chatterbox/models/s3tokenizer/__init__.py
chatterbox/models/s3tokenizer/s3tokenizer.py
chatterbox/models/t3/__init__.py
chatterbox/models/t3/llama_configs.py
chatterbox/models/t3/t3.py
chatterbox/models/t3/inference/alignment_stream_analyzer.py
chatterbox/models/t3/inference/t3_hf_backend.py
chatterbox/models/t3/modules/cond_enc.py
chatterbox/models/t3/modules/learned_pos_emb.py
chatterbox/models/t3/modules/perceiver.py
chatterbox/models/t3/modules/t3_config.py
chatterbox/models/tokenizers/__init__.py
chatterbox/models/tokenizers/tokenizer.py
chatterbox/models/voice_encoder/__init__.py
chatterbox/models/voice_encoder/config.py
chatterbox/models/voice_encoder/melspec.py
chatterbox/models/voice_encoder/voice_encoder.py
chatterbox_tts-0.1.4.dist-info/licenses/LICENSE
chatterbox_tts-0.1.4.dist-info/METADATA
chatterbox_tts-0.1.4.dist-info/WHEEL
chatterbox_tts-0.1.4.dist-info/top_level.txt
chatterbox_tts-0.1.4.dist-info/RECORD
