Metadata-Version: 2.4
Name: chatterbox-tts
Version: 0.1.4
Summary: Chatterbox: Open Source TTS and Voice Conversion by Resemble AI
Author-email: resemble-ai <engineering@resemble.ai>
License: MIT License
Project-URL: Homepage, https://github.com/resemble-ai/chatterbox
Project-URL: Repository, https://github.com/resemble-ai/chatterbox
Requires-Python: >=3.10
License-File: LICENSE
Requires-Dist: numpy<1.26.0,>=1.24.0
Requires-Dist: librosa==0.11.0
Requires-Dist: s3tokenizer
Requires-Dist: torch==2.6.0
Requires-Dist: torchaudio==2.6.0
Requires-Dist: transformers==4.46.3
Requires-Dist: diffusers==0.29.0
Requires-Dist: resemble-perth==1.0.1
Requires-Dist: conformer==0.3.2
Requires-Dist: safetensors==0.5.3
Requires-Dist: pkuseg==0.0.25
Requires-Dist: pykakasi==2.3.0
Requires-Dist: gradio==5.44.1
Dynamic: license-file
